{"mean":{"confidence_interval":{"confidence_level":0.95,"lower_bound":52100.471458794666,"upper_bound":54233.611984204625},"point_estimate":53168.199970884605,"standard_error":543.5274514103442},"median":{"confidence_interval":{"confidence_level":0.95,"lower_bound":51071.71052631579,"upper_bound":54995.506471095774},"point_estimate":52953.02463980147,"standard_error":935.2767901741173},"median_abs_dev":{"confidence_interval":{"confidence_level":0.95,"lower_bound":4896.4768417579935,"upper_bound":7572.130774458978},"point_estimate":6430.270957361666,"standard_error":713.5833099834875},"slope":{"confidence_interval":{"confidence_level":0.95,"lower_bound":50736.41885000232,"upper_bound":53157.13958658452},"point_estimate":51906.295366056635,"standard_error":618.5554901203698},"std_dev":{"confidence_interval":{"confidence_level":0.95,"lower_bound":4815.439079505778,"upper_bound":6002.632062395227},"point_estimate":5445.669225875719,"standard_error":303.7465739920399}}