{"mean":{"confidence_interval":{"confidence_level":0.95,"lower_bound":804596.6196530631,"upper_bound":810758.7198425313},"point_estimate":807677.0677718213,"standard_error":1575.3610733444814},"median":{"confidence_interval":{"confidence_level":0.95,"lower_bound":803712.09,"upper_bound":813979.1721311476},"point_estimate":806987.9118589744,"standard_error":2381.4111700678372},"median_abs_dev":{"confidence_interval":{"confidence_level":0.95,"lower_bound":14527.659800494674,"upper_bound":21199.306045966205},"point_estimate":17904.91811940212,"standard_error":1635.621714710914},"slope":{"confidence_interval":{"confidence_level":0.95,"lower_bound":800039.5993058442,"upper_bound":806614.0918221992},"point_estimate":803091.2850140387,"standard_error":1676.0027128698791},"std_dev":{"confidence_interval":{"confidence_level":0.95,"lower_bound":14108.743260572797,"upper_bound":17464.639557544684},"point_estimate":15876.879732376523,"standard_error":858.000022046869}}